[{"type":0.0,"id":"OldBuilding","DontDestroy":0,"level":1,"presentHP":100,"totalHP":100,"mRow":1,"mCol":6,"coordinate":[0,0,0,1,1,0,1,1],"pivotObject":"0","pos":"11.175/0.001226068/3.349998","isRotation":0,"parentRow":-1,"parentCol":-1},{"type":0.0,"id":"OldBuilding","DontDestroy":0,"level":1,"presentHP":100,"totalHP":100,"mRow":0,"mCol":14,"coordinate":[0,0,0,1,1,0,1,1],"pivotObject":"0","pos":"4.46/0.0002461672/5.94003","isRotation":0,"parentRow":-1,"parentCol":-1},{"type":0.0,"id":"OldBuilding","DontDestroy":0,"level":1,"presentHP":100,"totalHP":100,"mRow":3,"mCol":9,"coordinate":[0,0,0,1,1,0,1,1],"pivotObject":"0","pos":"10.425/0.0002367496/5.201532","isRotation":0,"parentRow":-1,"parentCol":-1},{"type":0.0,"id":"OldBuilding","DontDestroy":0,"level":1,"presentHP":100,"totalHP":100,"mRow":3,"mCol":11,"coordinate":[0,0,0,1,1,0,1,1],"pivotObject":"0","pos":"8.934999/-0.003497124/5.94164","isRotation":0,"parentRow":-1,"parentCol":-1},{"type":0.0,"id":"OldBuilding","DontDestroy":0,"level":1,"presentHP":100,"totalHP":100,"mRow":2,"mCol":13,"coordinate":[0,0,0,1,1,0,1,1],"pivotObject":"0","pos":"6.7/0.0001525879/6.309921","isRotation":0,"parentRow":-1,"parentCol":-1},{"type":2.0,"id":"Guard","DontDestroy":0,"level":1,"presentHP":0,"totalHP":200,"mRow":8,"mCol":12,"coordinate":[0,0,0,1,1,0,1,1],"pivotObject":"0","pos":"11.91/-0.0005033016/8.160001","isRotation":0,"parentRow":-1,"parentCol":-1}]