[{"Level":1,"Price":1200,"UpgradeCost":2000,"CoolTime":1,"Attack":10,"DisassemblyTime":5,"Type":3,"id":"FlameThrowingTrap","SellPrice":600,"ActiveCost":8000,"EffectContinuousTime":3},
    {"Level":2,"Price":1300,"UpgradeCost":2080,"CoolTime":1,"Attack":12,"DisassemblyTime":5,"Type":3,"id":"FlameThrowingTrap","SellPrice":650,"ActiveCost":8000,"EffectContinuousTime":3},
    {"Level":3,"Price":1400,"UpgradeCost":2160,"CoolTime":1,"Attack":14,"DisassemblyTime":5,"Type":3,"id":"FlameThrowingTrap","SellPrice":700,"ActiveCost":8000,"EffectContinuousTime":3},
    {"Level":4,"Price":1500,"UpgradeCost":2240,"CoolTime":1,"Attack":16,"DisassemblyTime":5,"Type":3,"id":"FlameThrowingTrap","SellPrice":750,"ActiveCost":8000,"EffectContinuousTime":3},
    {"Level":5,"Price":1600,"UpgradeCost":2320,"CoolTime":1,"Attack":18,"DisassemblyTime":5,"Type":3,"id":"FlameThrowingTrap","SellPrice":800,"ActiveCost":8000,"EffectContinuousTime":3},
    {"Level":6,"Price":1700,"UpgradeCost":2400,"CoolTime":1,"Attack":20,"DisassemblyTime":5,"Type":3,"id":"FlameThrowingTrap","SellPrice":850,"ActiveCost":8000,"EffectContinuousTime":3},
    {"Level":7,"Price":1800,"UpgradeCost":2480,"CoolTime":1,"Attack":22,"DisassemblyTime":5,"Type":3,"id":"FlameThrowingTrap","SellPrice":900,"ActiveCost":8000,"EffectContinuousTime":3},
    {"Level":8,"Price":1900,"UpgradeCost":2560,"CoolTime":1,"Attack":24,"DisassemblyTime":5,"Type":3,"id":"FlameThrowingTrap","SellPrice":950,"ActiveCost":8000,"EffectContinuousTime":3},
    {"Level":9,"Price":2000,"UpgradeCost":2640,"CoolTime":1,"Attack":26,"DisassemblyTime":5,"Type":3,"id":"FlameThrowingTrap","SellPrice":1000,"ActiveCost":8000,"EffectContinuousTime":3},
    {"Level":10,"Price":2100,"UpgradeCost":2720,"CoolTime":1,"Attack":28,"DisassemblyTime":5,"Type":3,"id":"FlameThrowingTrap","SellPrice":1050,"ActiveCost":8000,"EffectContinuousTime":3},
    {"Level":11,"Price":2200,"UpgradeCost":2800,"CoolTime":1,"Attack":30,"DisassemblyTime":5,"Type":3,"id":"FlameThrowingTrap","SellPrice":1100,"ActiveCost":8000,"EffectContinuousTime":3},
    {"Level":12,"Price":2300,"UpgradeCost":2880,"CoolTime":1,"Attack":32,"DisassemblyTime":5,"Type":3,"id":"FlameThrowingTrap","SellPrice":1150,"ActiveCost":8000,"EffectContinuousTime":3},
    {"Level":13,"Price":2400,"UpgradeCost":2960,"CoolTime":1,"Attack":34,"DisassemblyTime":5,"Type":3,"id":"FlameThrowingTrap","SellPrice":1200,"ActiveCost":8000,"EffectContinuousTime":3},
    {"Level":14,"Price":2500,"UpgradeCost":3040,"CoolTime":1,"Attack":36,"DisassemblyTime":5,"Type":3,"id":"FlameThrowingTrap","SellPrice":1250,"ActiveCost":8000,"EffectContinuousTime":3},
    {"Level":15,"Price":2600,"UpgradeCost":3120,"CoolTime":1,"Attack":38,"DisassemblyTime":5,"Type":3,"id":"FlameThrowingTrap","SellPrice":1300,"ActiveCost":8000,"EffectContinuousTime":3},
    {"Level":16,"Price":2700,"UpgradeCost":3200,"CoolTime":1,"Attack":40,"DisassemblyTime":5,"Type":3,"id":"FlameThrowingTrap","SellPrice":1350,"ActiveCost":8000,"EffectContinuousTime":3},
    {"Level":17,"Price":2800,"UpgradeCost":3280,"CoolTime":1,"Attack":42,"DisassemblyTime":5,"Type":3,"id":"FlameThrowingTrap","SellPrice":1400,"ActiveCost":8000,"EffectContinuousTime":3},
    {"Level":18,"Price":2900,"UpgradeCost":3360,"CoolTime":1,"Attack":44,"DisassemblyTime":5,"Type":3,"id":"FlameThrowingTrap","SellPrice":1450,"ActiveCost":8000,"EffectContinuousTime":3},
    {"Level":19,"Price":3000,"UpgradeCost":3440,"CoolTime":1,"Attack":46,"DisassemblyTime":5,"Type":3,"id":"FlameThrowingTrap","SellPrice":1500,"ActiveCost":8000,"EffectContinuousTime":3},
    {"Level":20,"Price":3100,"UpgradeCost":3520,"CoolTime":1,"Attack":48,"DisassemblyTime":5,"Type":3,"id":"FlameThrowingTrap","SellPrice":1550,"ActiveCost":8000,"EffectContinuousTime":3},
    {"Level":21,"Price":3200,"UpgradeCost":3600,"CoolTime":1,"Attack":50,"DisassemblyTime":5.5,"Type":3,"id":"FlameThrowingTrap","SellPrice":1600,"ActiveCost":8000,"EffectContinuousTime":3},
    {"Level":22,"Price":3300,"UpgradeCost":3680,"CoolTime":1,"Attack":52,"DisassemblyTime":5.5,"Type":3,"id":"FlameThrowingTrap","SellPrice":1650,"ActiveCost":8000,"EffectContinuousTime":3},
    {"Level":23,"Price":3400,"UpgradeCost":3760,"CoolTime":1,"Attack":54,"DisassemblyTime":5.5,"Type":3,"id":"FlameThrowingTrap","SellPrice":1700,"ActiveCost":8000,"EffectContinuousTime":3},
    {"Level":24,"Price":3500,"UpgradeCost":3840,"CoolTime":1,"Attack":56,"DisassemblyTime":5.5,"Type":3,"id":"FlameThrowingTrap","SellPrice":1750,"ActiveCost":8000,"EffectContinuousTime":3},
    {"Level":25,"Price":3600,"UpgradeCost":3920,"CoolTime":1,"Attack":58,"DisassemblyTime":5.5,"Type":3,"id":"FlameThrowingTrap","SellPrice":1800,"ActiveCost":8000,"EffectContinuousTime":3},
    {"Level":26,"Price":3700,"UpgradeCost":4000,"CoolTime":1,"Attack":60,"DisassemblyTime":5.5,"Type":3,"id":"FlameThrowingTrap","SellPrice":1850,"ActiveCost":8000,"EffectContinuousTime":3},
    {"Level":27,"Price":3800,"UpgradeCost":4080,"CoolTime":1,"Attack":62,"DisassemblyTime":5.5,"Type":3,"id":"FlameThrowingTrap","SellPrice":1900,"ActiveCost":8000,"EffectContinuousTime":3},
    {"Level":28,"Price":3900,"UpgradeCost":4160,"CoolTime":1,"Attack":64,"DisassemblyTime":5.5,"Type":3,"id":"FlameThrowingTrap","SellPrice":1950,"ActiveCost":8000,"EffectContinuousTime":3},
    {"Level":29,"Price":4000,"UpgradeCost":4240,"CoolTime":1,"Attack":66,"DisassemblyTime":5.5,"Type":3,"id":"FlameThrowingTrap","SellPrice":2000,"ActiveCost":8000,"EffectContinuousTime":3},
    {"Level":30,"Price":4100,"UpgradeCost":4320,"CoolTime":1,"Attack":68,"DisassemblyTime":5.5,"Type":3,"id":"FlameThrowingTrap","SellPrice":2050,"ActiveCost":8000,"EffectContinuousTime":3},
    {"Level":31,"Price":4200,"UpgradeCost":4400,"CoolTime":1,"Attack":70,"DisassemblyTime":5.5,"Type":3,"id":"FlameThrowingTrap","SellPrice":2100,"ActiveCost":8000,"EffectContinuousTime":3},
    {"Level":32,"Price":4300,"UpgradeCost":4480,"CoolTime":1,"Attack":72,"DisassemblyTime":5.5,"Type":3,"id":"FlameThrowingTrap","SellPrice":2150,"ActiveCost":8000,"EffectContinuousTime":3},
    {"Level":33,"Price":4400,"UpgradeCost":4560,"CoolTime":1,"Attack":74,"DisassemblyTime":5.5,"Type":3,"id":"FlameThrowingTrap","SellPrice":2200,"ActiveCost":8000,"EffectContinuousTime":3},
    {"Level":34,"Price":4500,"UpgradeCost":4640,"CoolTime":1,"Attack":76,"DisassemblyTime":5.5,"Type":3,"id":"FlameThrowingTrap","SellPrice":2250,"ActiveCost":8000,"EffectContinuousTime":3},
    {"Level":35,"Price":4600,"UpgradeCost":4720,"CoolTime":1,"Attack":78,"DisassemblyTime":5.5,"Type":3,"id":"FlameThrowingTrap","SellPrice":2300,"ActiveCost":8000,"EffectContinuousTime":3},
    {"Level":36,"Price":4700,"UpgradeCost":4800,"CoolTime":1,"Attack":80,"DisassemblyTime":5.5,"Type":3,"id":"FlameThrowingTrap","SellPrice":2350,"ActiveCost":8000,"EffectContinuousTime":3},
    {"Level":37,"Price":4800,"UpgradeCost":4880,"CoolTime":1,"Attack":82,"DisassemblyTime":5.5,"Type":3,"id":"FlameThrowingTrap","SellPrice":2400,"ActiveCost":8000,"EffectContinuousTime":3},
    {"Level":38,"Price":4900,"UpgradeCost":4960,"CoolTime":1,"Attack":84,"DisassemblyTime":5.5,"Type":3,"id":"FlameThrowingTrap","SellPrice":2450,"ActiveCost":8000,"EffectContinuousTime":3},
    {"Level":39,"Price":5000,"UpgradeCost":5040,"CoolTime":1,"Attack":86,"DisassemblyTime":5.5,"Type":3,"id":"FlameThrowingTrap","SellPrice":2500,"ActiveCost":8000,"EffectContinuousTime":3},
    {"Level":40,"Price":5100,"UpgradeCost":5120,"CoolTime":1,"Attack":88,"DisassemblyTime":5.5,"Type":3,"id":"FlameThrowingTrap","SellPrice":2550,"ActiveCost":8000,"EffectContinuousTime":3},
    {"Level":41,"Price":5200,"UpgradeCost":5200,"CoolTime":1,"Attack":90,"DisassemblyTime":6,"Type":3,"id":"FlameThrowingTrap","SellPrice":2600,"ActiveCost":8000,"EffectContinuousTime":3},
    {"Level":42,"Price":5300,"UpgradeCost":5280,"CoolTime":1,"Attack":92,"DisassemblyTime":6,"Type":3,"id":"FlameThrowingTrap","SellPrice":2650,"ActiveCost":8000,"EffectContinuousTime":3},
    {"Level":43,"Price":5400,"UpgradeCost":5360,"CoolTime":1,"Attack":94,"DisassemblyTime":6,"Type":3,"id":"FlameThrowingTrap","SellPrice":2700,"ActiveCost":8000,"EffectContinuousTime":3},
    {"Level":44,"Price":5500,"UpgradeCost":5440,"CoolTime":1,"Attack":96,"DisassemblyTime":6,"Type":3,"id":"FlameThrowingTrap","SellPrice":2750,"ActiveCost":8000,"EffectContinuousTime":3},
    {"Level":45,"Price":5600,"UpgradeCost":5520,"CoolTime":1,"Attack":98,"DisassemblyTime":6,"Type":3,"id":"FlameThrowingTrap","SellPrice":2800,"ActiveCost":8000,"EffectContinuousTime":3},
    {"Level":46,"Price":5700,"UpgradeCost":5600,"CoolTime":1,"Attack":100,"DisassemblyTime":6,"Type":3,"id":"FlameThrowingTrap","SellPrice":2850,"ActiveCost":8000,"EffectContinuousTime":3},
    {"Level":47,"Price":5800,"UpgradeCost":5680,"CoolTime":1,"Attack":102,"DisassemblyTime":6,"Type":3,"id":"FlameThrowingTrap","SellPrice":2900,"ActiveCost":8000,"EffectContinuousTime":3},
    {"Level":48,"Price":5900,"UpgradeCost":5760,"CoolTime":1,"Attack":104,"DisassemblyTime":6,"Type":3,"id":"FlameThrowingTrap","SellPrice":2950,"ActiveCost":8000,"EffectContinuousTime":3},
    {"Level":49,"Price":6000,"UpgradeCost":5840,"CoolTime":1,"Attack":106,"DisassemblyTime":6,"Type":3,"id":"FlameThrowingTrap","SellPrice":3000,"ActiveCost":8000,"EffectContinuousTime":3},
    {"Level":50,"Price":6100,"UpgradeCost":5920,"CoolTime":1,"Attack":108,"DisassemblyTime":6,"Type":3,"id":"FlameThrowingTrap","SellPrice":3050,"ActiveCost":8000,"EffectContinuousTime":3},
    {"Level":51,"Price":6200,"UpgradeCost":6000,"CoolTime":1,"Attack":110,"DisassemblyTime":6,"Type":3,"id":"FlameThrowingTrap","SellPrice":3100,"ActiveCost":8000,"EffectContinuousTime":3},
    {"Level":52,"Price":6300,"UpgradeCost":6080,"CoolTime":1,"Attack":112,"DisassemblyTime":6,"Type":3,"id":"FlameThrowingTrap","SellPrice":3150,"ActiveCost":8000,"EffectContinuousTime":3},
    {"Level":53,"Price":6400,"UpgradeCost":6160,"CoolTime":1,"Attack":114,"DisassemblyTime":6,"Type":3,"id":"FlameThrowingTrap","SellPrice":3200,"ActiveCost":8000,"EffectContinuousTime":3},
    {"Level":54,"Price":6500,"UpgradeCost":6240,"CoolTime":1,"Attack":116,"DisassemblyTime":6,"Type":3,"id":"FlameThrowingTrap","SellPrice":3250,"ActiveCost":8000,"EffectContinuousTime":3},
    {"Level":55,"Price":6600,"UpgradeCost":6320,"CoolTime":1,"Attack":118,"DisassemblyTime":6,"Type":3,"id":"FlameThrowingTrap","SellPrice":3300,"ActiveCost":8000,"EffectContinuousTime":3},
    {"Level":56,"Price":6700,"UpgradeCost":6400,"CoolTime":1,"Attack":120,"DisassemblyTime":6,"Type":3,"id":"FlameThrowingTrap","SellPrice":3350,"ActiveCost":8000,"EffectContinuousTime":3},
    {"Level":57,"Price":6800,"UpgradeCost":6480,"CoolTime":1,"Attack":122,"DisassemblyTime":6,"Type":3,"id":"FlameThrowingTrap","SellPrice":3400,"ActiveCost":8000,"EffectContinuousTime":3},
    {"Level":58,"Price":6900,"UpgradeCost":6560,"CoolTime":1,"Attack":124,"DisassemblyTime":6,"Type":3,"id":"FlameThrowingTrap","SellPrice":3450,"ActiveCost":8000,"EffectContinuousTime":3},
    {"Level":59,"Price":7000,"UpgradeCost":6640,"CoolTime":1,"Attack":126,"DisassemblyTime":6,"Type":3,"id":"FlameThrowingTrap","SellPrice":3500,"ActiveCost":8000,"EffectContinuousTime":3},
    {"Level":60,"Price":7100,"UpgradeCost":6720,"CoolTime":1,"Attack":128,"DisassemblyTime":6,"Type":3,"id":"FlameThrowingTrap","SellPrice":3550,"ActiveCost":8000,"EffectContinuousTime":3},
    {"Level":61,"Price":7200,"UpgradeCost":6800,"CoolTime":1,"Attack":130,"DisassemblyTime":6.5,"Type":3,"id":"FlameThrowingTrap","SellPrice":3600,"ActiveCost":8000,"EffectContinuousTime":3},
    {"Level":62,"Price":7300,"UpgradeCost":6880,"CoolTime":1,"Attack":132,"DisassemblyTime":6.5,"Type":3,"id":"FlameThrowingTrap","SellPrice":3650,"ActiveCost":8000,"EffectContinuousTime":3},
    {"Level":63,"Price":7400,"UpgradeCost":6960,"CoolTime":1,"Attack":134,"DisassemblyTime":6.5,"Type":3,"id":"FlameThrowingTrap","SellPrice":3700,"ActiveCost":8000,"EffectContinuousTime":3},
    {"Level":64,"Price":7500,"UpgradeCost":7040,"CoolTime":1,"Attack":136,"DisassemblyTime":6.5,"Type":3,"id":"FlameThrowingTrap","SellPrice":3750,"ActiveCost":8000,"EffectContinuousTime":3},
    {"Level":65,"Price":7600,"UpgradeCost":7120,"CoolTime":1,"Attack":138,"DisassemblyTime":6.5,"Type":3,"id":"FlameThrowingTrap","SellPrice":3800,"ActiveCost":8000,"EffectContinuousTime":3},
    {"Level":66,"Price":7700,"UpgradeCost":7200,"CoolTime":1,"Attack":140,"DisassemblyTime":6.5,"Type":3,"id":"FlameThrowingTrap","SellPrice":3850,"ActiveCost":8000,"EffectContinuousTime":3},
    {"Level":67,"Price":7800,"UpgradeCost":7280,"CoolTime":1,"Attack":142,"DisassemblyTime":6.5,"Type":3,"id":"FlameThrowingTrap","SellPrice":3900,"ActiveCost":8000,"EffectContinuousTime":3},
    {"Level":68,"Price":7900,"UpgradeCost":7360,"CoolTime":1,"Attack":144,"DisassemblyTime":6.5,"Type":3,"id":"FlameThrowingTrap","SellPrice":3950,"ActiveCost":8000,"EffectContinuousTime":3},
    {"Level":69,"Price":8000,"UpgradeCost":7440,"CoolTime":1,"Attack":146,"DisassemblyTime":6.5,"Type":3,"id":"FlameThrowingTrap","SellPrice":4000,"ActiveCost":8000,"EffectContinuousTime":3},
    {"Level":70,"Price":8100,"UpgradeCost":7520,"CoolTime":1,"Attack":148,"DisassemblyTime":6.5,"Type":3,"id":"FlameThrowingTrap","SellPrice":4050,"ActiveCost":8000,"EffectContinuousTime":3},
    {"Level":71,"Price":8200,"UpgradeCost":7600,"CoolTime":1,"Attack":150,"DisassemblyTime":6.5,"Type":3,"id":"FlameThrowingTrap","SellPrice":4100,"ActiveCost":8000,"EffectContinuousTime":3},
    {"Level":72,"Price":8300,"UpgradeCost":7680,"CoolTime":1,"Attack":152,"DisassemblyTime":6.5,"Type":3,"id":"FlameThrowingTrap","SellPrice":4150,"ActiveCost":8000,"EffectContinuousTime":3},
    {"Level":73,"Price":8400,"UpgradeCost":7760,"CoolTime":1,"Attack":154,"DisassemblyTime":6.5,"Type":3,"id":"FlameThrowingTrap","SellPrice":4200,"ActiveCost":8000,"EffectContinuousTime":3},
    {"Level":74,"Price":8500,"UpgradeCost":7840,"CoolTime":1,"Attack":156,"DisassemblyTime":6.5,"Type":3,"id":"FlameThrowingTrap","SellPrice":4250,"ActiveCost":8000,"EffectContinuousTime":3},
    {"Level":75,"Price":8600,"UpgradeCost":7920,"CoolTime":1,"Attack":158,"DisassemblyTime":6.5,"Type":3,"id":"FlameThrowingTrap","SellPrice":4300,"ActiveCost":8000,"EffectContinuousTime":3},
    {"Level":76,"Price":8700,"UpgradeCost":8000,"CoolTime":1,"Attack":160,"DisassemblyTime":6.5,"Type":3,"id":"FlameThrowingTrap","SellPrice":4350,"ActiveCost":8000,"EffectContinuousTime":3},
    {"Level":77,"Price":8800,"UpgradeCost":8080,"CoolTime":1,"Attack":162,"DisassemblyTime":6.5,"Type":3,"id":"FlameThrowingTrap","SellPrice":4400,"ActiveCost":8000,"EffectContinuousTime":3},
    {"Level":78,"Price":8900,"UpgradeCost":8160,"CoolTime":1,"Attack":164,"DisassemblyTime":6.5,"Type":3,"id":"FlameThrowingTrap","SellPrice":4450,"ActiveCost":8000,"EffectContinuousTime":3},
    {"Level":79,"Price":9000,"UpgradeCost":8240,"CoolTime":1,"Attack":166,"DisassemblyTime":6.5,"Type":3,"id":"FlameThrowingTrap","SellPrice":4500,"ActiveCost":8000,"EffectContinuousTime":3},
    {"Level":80,"Price":9100,"UpgradeCost":8320,"CoolTime":1,"Attack":168,"DisassemblyTime":6.5,"Type":3,"id":"FlameThrowingTrap","SellPrice":4550,"ActiveCost":8000,"EffectContinuousTime":3},
    {"Level":81,"Price":9200,"UpgradeCost":8400,"CoolTime":1,"Attack":170,"DisassemblyTime":7,"Type":3,"id":"FlameThrowingTrap","SellPrice":4600,"ActiveCost":8000,"EffectContinuousTime":3},
    {"Level":82,"Price":9300,"UpgradeCost":8480,"CoolTime":1,"Attack":172,"DisassemblyTime":7,"Type":3,"id":"FlameThrowingTrap","SellPrice":4650,"ActiveCost":8000,"EffectContinuousTime":3},
    {"Level":83,"Price":9400,"UpgradeCost":8560,"CoolTime":1,"Attack":174,"DisassemblyTime":7,"Type":3,"id":"FlameThrowingTrap","SellPrice":4700,"ActiveCost":8000,"EffectContinuousTime":3},
    {"Level":84,"Price":9500,"UpgradeCost":8640,"CoolTime":1,"Attack":176,"DisassemblyTime":7,"Type":3,"id":"FlameThrowingTrap","SellPrice":4750,"ActiveCost":8000,"EffectContinuousTime":3},
    {"Level":85,"Price":9600,"UpgradeCost":8720,"CoolTime":1,"Attack":178,"DisassemblyTime":7,"Type":3,"id":"FlameThrowingTrap","SellPrice":4800,"ActiveCost":8000,"EffectContinuousTime":3},
    {"Level":86,"Price":9700,"UpgradeCost":8800,"CoolTime":1,"Attack":180,"DisassemblyTime":7,"Type":3,"id":"FlameThrowingTrap","SellPrice":4850,"ActiveCost":8000,"EffectContinuousTime":3},
    {"Level":87,"Price":9800,"UpgradeCost":8880,"CoolTime":1,"Attack":182,"DisassemblyTime":7,"Type":3,"id":"FlameThrowingTrap","SellPrice":4900,"ActiveCost":8000,"EffectContinuousTime":3},
    {"Level":88,"Price":9900,"UpgradeCost":8960,"CoolTime":1,"Attack":184,"DisassemblyTime":7,"Type":3,"id":"FlameThrowingTrap","SellPrice":4950,"ActiveCost":8000,"EffectContinuousTime":3},
    {"Level":89,"Price":10000,"UpgradeCost":9040,"CoolTime":1,"Attack":186,"DisassemblyTime":7,"Type":3,"id":"FlameThrowingTrap","SellPrice":5000,"ActiveCost":8000,"EffectContinuousTime":3},
    {"Level":90,"Price":10100,"UpgradeCost":9120,"CoolTime":1,"Attack":188,"DisassemblyTime":7,"Type":3,"id":"FlameThrowingTrap","SellPrice":5050,"ActiveCost":8000,"EffectContinuousTime":3},
    {"Level":91,"Price":10200,"UpgradeCost":9200,"CoolTime":1,"Attack":190,"DisassemblyTime":7,"Type":3,"id":"FlameThrowingTrap","SellPrice":5100,"ActiveCost":8000,"EffectContinuousTime":3},
    {"Level":92,"Price":10300,"UpgradeCost":9280,"CoolTime":1,"Attack":192,"DisassemblyTime":7,"Type":3,"id":"FlameThrowingTrap","SellPrice":5150,"ActiveCost":8000,"EffectContinuousTime":3},
    {"Level":93,"Price":10400,"UpgradeCost":9360,"CoolTime":1,"Attack":194,"DisassemblyTime":7,"Type":3,"id":"FlameThrowingTrap","SellPrice":5200,"ActiveCost":8000,"EffectContinuousTime":3},
    {"Level":94,"Price":10500,"UpgradeCost":9440,"CoolTime":1,"Attack":196,"DisassemblyTime":7,"Type":3,"id":"FlameThrowingTrap","SellPrice":5250,"ActiveCost":8000,"EffectContinuousTime":3},
    {"Level":95,"Price":10600,"UpgradeCost":9520,"CoolTime":1,"Attack":198,"DisassemblyTime":7,"Type":3,"id":"FlameThrowingTrap","SellPrice":5300,"ActiveCost":8000,"EffectContinuousTime":3},
    {"Level":96,"Price":10700,"UpgradeCost":9600,"CoolTime":1,"Attack":200,"DisassemblyTime":7,"Type":3,"id":"FlameThrowingTrap","SellPrice":5350,"ActiveCost":8000,"EffectContinuousTime":3},
    {"Level":97,"Price":10800,"UpgradeCost":9680,"CoolTime":1,"Attack":202,"DisassemblyTime":7,"Type":3,"id":"FlameThrowingTrap","SellPrice":5400,"ActiveCost":8000,"EffectContinuousTime":3},
    {"Level":98,"Price":10900,"UpgradeCost":9760,"CoolTime":1,"Attack":204,"DisassemblyTime":7,"Type":3,"id":"FlameThrowingTrap","SellPrice":5450,"ActiveCost":8000,"EffectContinuousTime":3},
    {"Level":99,"Price":11000,"UpgradeCost":9840,"CoolTime":1,"Attack":206,"DisassemblyTime":7,"Type":3,"id":"FlameThrowingTrap","SellPrice":5500,"ActiveCost":8000,"EffectContinuousTime":3},
    {"Level":100,"Price":11100,"UpgradeCost":9920,"CoolTime":1,"Attack":208,"DisassemblyTime":7,"Type":3,"id":"FlameThrowingTrap","SellPrice":5550,"ActiveCost":8000,"EffectContinuousTime":3}]