[{"Level":1,"Attack":0,"Price":500,"UpgradeCost":700,"CoolTime":10,"DisassemblyTime":5,"Type":3,"id":"HumanTrap","SellPrice":250},
    {"Level":2,"Attack":0,"Price":500,"UpgradeCost":730,"CoolTime":10,"DisassemblyTime":5,"Type":3,"id":"HumanTrap","SellPrice":250},
    {"Level":3,"Attack":0,"Price":500,"UpgradeCost":760,"CoolTime":10,"DisassemblyTime":5,"Type":3,"id":"HumanTrap","SellPrice":250},
    {"Level":4,"Attack":0,"Price":500,"UpgradeCost":790,"CoolTime":10,"DisassemblyTime":5,"Type":3,"id":"HumanTrap","SellPrice":250},
    {"Level":5,"Attack":0,"Price":500,"UpgradeCost":820,"CoolTime":10,"DisassemblyTime":5,"Type":3,"id":"HumanTrap","SellPrice":250},
    {"Level":6,"Attack":0,"Price":500,"UpgradeCost":850,"CoolTime":10,"DisassemblyTime":5,"Type":3,"id":"HumanTrap","SellPrice":250},
    {"Level":7,"Attack":0,"Price":500,"UpgradeCost":880,"CoolTime":10,"DisassemblyTime":5,"Type":3,"id":"HumanTrap","SellPrice":250},
    {"Level":8,"Attack":0,"Price":500,"UpgradeCost":910,"CoolTime":10,"DisassemblyTime":5,"Type":3,"id":"HumanTrap","SellPrice":250},
    {"Level":9,"Attack":0,"Price":500,"UpgradeCost":940,"CoolTime":10,"DisassemblyTime":5,"Type":3,"id":"HumanTrap","SellPrice":250},
    {"Level":10,"Attack":0,"Price":500,"UpgradeCost":970,"CoolTime":10,"DisassemblyTime":5,"Type":3,"id":"HumanTrap","SellPrice":250},
    {"Level":11,"Attack":0,"Price":1000,"UpgradeCost":1000,"CoolTime":9.5,"DisassemblyTime":5,"Type":3,"id":"HumanTrap","SellPrice":500},
    {"Level":12,"Attack":0,"Price":1000,"UpgradeCost":1030,"CoolTime":9.5,"DisassemblyTime":5,"Type":3,"id":"HumanTrap","SellPrice":500},
    {"Level":13,"Attack":0,"Price":1000,"UpgradeCost":1060,"CoolTime":9.5,"DisassemblyTime":5,"Type":3,"id":"HumanTrap","SellPrice":500},
    {"Level":14,"Attack":0,"Price":1000,"UpgradeCost":1090,"CoolTime":9.5,"DisassemblyTime":5,"Type":3,"id":"HumanTrap","SellPrice":500},
    {"Level":15,"Attack":0,"Price":1000,"UpgradeCost":1120,"CoolTime":9.5,"DisassemblyTime":5,"Type":3,"id":"HumanTrap","SellPrice":500},
    {"Level":16,"Attack":0,"Price":1000,"UpgradeCost":1150,"CoolTime":9.5,"DisassemblyTime":5,"Type":3,"id":"HumanTrap","SellPrice":500},
    {"Level":17,"Attack":0,"Price":1000,"UpgradeCost":1180,"CoolTime":9.5,"DisassemblyTime":5,"Type":3,"id":"HumanTrap","SellPrice":500},
    {"Level":18,"Attack":0,"Price":1000,"UpgradeCost":1210,"CoolTime":9.5,"DisassemblyTime":5,"Type":3,"id":"HumanTrap","SellPrice":500},
    {"Level":19,"Attack":0,"Price":1000,"UpgradeCost":1240,"CoolTime":9.5,"DisassemblyTime":5,"Type":3,"id":"HumanTrap","SellPrice":500},
    {"Level":20,"Attack":0,"Price":1000,"UpgradeCost":1270,"CoolTime":9.5,"DisassemblyTime":5,"Type":3,"id":"HumanTrap","SellPrice":500},
    {"Level":21,"Attack":0,"Price":1500,"UpgradeCost":1300,"CoolTime":9,"DisassemblyTime":5,"Type":3,"id":"HumanTrap","SellPrice":750},
    {"Level":22,"Attack":0,"Price":1500,"UpgradeCost":1330,"CoolTime":9,"DisassemblyTime":5,"Type":3,"id":"HumanTrap","SellPrice":750},
    {"Level":23,"Attack":0,"Price":1500,"UpgradeCost":1360,"CoolTime":9,"DisassemblyTime":5,"Type":3,"id":"HumanTrap","SellPrice":750},
    {"Level":24,"Attack":0,"Price":1500,"UpgradeCost":1390,"CoolTime":9,"DisassemblyTime":5,"Type":3,"id":"HumanTrap","SellPrice":750},
    {"Level":25,"Attack":0,"Price":1500,"UpgradeCost":1420,"CoolTime":9,"DisassemblyTime":5,"Type":3,"id":"HumanTrap","SellPrice":750},
    {"Level":26,"Attack":0,"Price":1500,"UpgradeCost":1450,"CoolTime":9,"DisassemblyTime":5,"Type":3,"id":"HumanTrap","SellPrice":750},
    {"Level":27,"Attack":0,"Price":1500,"UpgradeCost":1480,"CoolTime":9,"DisassemblyTime":5,"Type":3,"id":"HumanTrap","SellPrice":750},
    {"Level":28,"Attack":0,"Price":1500,"UpgradeCost":1510,"CoolTime":9,"DisassemblyTime":5,"Type":3,"id":"HumanTrap","SellPrice":750},
    {"Level":29,"Attack":0,"Price":1500,"UpgradeCost":1540,"CoolTime":9,"DisassemblyTime":5,"Type":3,"id":"HumanTrap","SellPrice":750},
    {"Level":30,"Attack":0,"Price":1500,"UpgradeCost":1570,"CoolTime":9,"DisassemblyTime":5,"Type":3,"id":"HumanTrap","SellPrice":750},
    {"Level":31,"Attack":0,"Price":2000,"UpgradeCost":1600,"CoolTime":8.5,"DisassemblyTime":5,"Type":3,"id":"HumanTrap","SellPrice":1000},
    {"Level":32,"Attack":0,"Price":2000,"UpgradeCost":1630,"CoolTime":8.5,"DisassemblyTime":5,"Type":3,"id":"HumanTrap","SellPrice":1000},
    {"Level":33,"Attack":0,"Price":2000,"UpgradeCost":1660,"CoolTime":8.5,"DisassemblyTime":5,"Type":3,"id":"HumanTrap","SellPrice":1000},
    {"Level":34,"Attack":0,"Price":2000,"UpgradeCost":1690,"CoolTime":8.5,"DisassemblyTime":5,"Type":3,"id":"HumanTrap","SellPrice":1000},
    {"Level":35,"Attack":0,"Price":2000,"UpgradeCost":1720,"CoolTime":8.5,"DisassemblyTime":5,"Type":3,"id":"HumanTrap","SellPrice":1000},
    {"Level":36,"Attack":0,"Price":2000,"UpgradeCost":1750,"CoolTime":8.5,"DisassemblyTime":5,"Type":3,"id":"HumanTrap","SellPrice":1000},
    {"Level":37,"Attack":0,"Price":2000,"UpgradeCost":1780,"CoolTime":8.5,"DisassemblyTime":5,"Type":3,"id":"HumanTrap","SellPrice":1000},
    {"Level":38,"Attack":0,"Price":2000,"UpgradeCost":1810,"CoolTime":8.5,"DisassemblyTime":5,"Type":3,"id":"HumanTrap","SellPrice":1000},
    {"Level":39,"Attack":0,"Price":2000,"UpgradeCost":1840,"CoolTime":8.5,"DisassemblyTime":5,"Type":3,"id":"HumanTrap","SellPrice":1000},
    {"Level":40,"Attack":0,"Price":2000,"UpgradeCost":1870,"CoolTime":8.5,"DisassemblyTime":5,"Type":3,"id":"HumanTrap","SellPrice":1000},
    {"Level":41,"Attack":0,"Price":2500,"UpgradeCost":1900,"CoolTime":8,"DisassemblyTime":5,"Type":3,"id":"HumanTrap","SellPrice":1250},
    {"Level":42,"Attack":0,"Price":2500,"UpgradeCost":1930,"CoolTime":8,"DisassemblyTime":5,"Type":3,"id":"HumanTrap","SellPrice":1250},
    {"Level":43,"Attack":0,"Price":2500,"UpgradeCost":1960,"CoolTime":8,"DisassemblyTime":5,"Type":3,"id":"HumanTrap","SellPrice":1250},
    {"Level":44,"Attack":0,"Price":2500,"UpgradeCost":1990,"CoolTime":8,"DisassemblyTime":5,"Type":3,"id":"HumanTrap","SellPrice":1250},
    {"Level":45,"Attack":0,"Price":2500,"UpgradeCost":2020,"CoolTime":8,"DisassemblyTime":5,"Type":3,"id":"HumanTrap","SellPrice":1250},
    {"Level":46,"Attack":0,"Price":2500,"UpgradeCost":2050,"CoolTime":8,"DisassemblyTime":5,"Type":3,"id":"HumanTrap","SellPrice":1250},
    {"Level":47,"Attack":0,"Price":2500,"UpgradeCost":2080,"CoolTime":8,"DisassemblyTime":5,"Type":3,"id":"HumanTrap","SellPrice":1250},
    {"Level":48,"Attack":0,"Price":2500,"UpgradeCost":2110,"CoolTime":8,"DisassemblyTime":5,"Type":3,"id":"HumanTrap","SellPrice":1250},
    {"Level":49,"Attack":0,"Price":2500,"UpgradeCost":2140,"CoolTime":8,"DisassemblyTime":5,"Type":3,"id":"HumanTrap","SellPrice":1250},
    {"Level":50,"Attack":0,"Price":2500,"UpgradeCost":2170,"CoolTime":8,"DisassemblyTime":5,"Type":3,"id":"HumanTrap","SellPrice":1250},
    {"Level":51,"Attack":0,"Price":3000,"UpgradeCost":2200,"CoolTime":7.5,"DisassemblyTime":5,"Type":3,"id":"HumanTrap","SellPrice":1500},
    {"Level":52,"Attack":0,"Price":3000,"UpgradeCost":2230,"CoolTime":7.5,"DisassemblyTime":5,"Type":3,"id":"HumanTrap","SellPrice":1500},
    {"Level":53,"Attack":0,"Price":3000,"UpgradeCost":2260,"CoolTime":7.5,"DisassemblyTime":5,"Type":3,"id":"HumanTrap","SellPrice":1500},
    {"Level":54,"Attack":0,"Price":3000,"UpgradeCost":2290,"CoolTime":7.5,"DisassemblyTime":5,"Type":3,"id":"HumanTrap","SellPrice":1500},
    {"Level":55,"Attack":0,"Price":3000,"UpgradeCost":2320,"CoolTime":7.5,"DisassemblyTime":5,"Type":3,"id":"HumanTrap","SellPrice":1500},
    {"Level":56,"Attack":0,"Price":3000,"UpgradeCost":2350,"CoolTime":7.5,"DisassemblyTime":5,"Type":3,"id":"HumanTrap","SellPrice":1500},
    {"Level":57,"Attack":0,"Price":3000,"UpgradeCost":2380,"CoolTime":7.5,"DisassemblyTime":5,"Type":3,"id":"HumanTrap","SellPrice":1500},
    {"Level":58,"Attack":0,"Price":3000,"UpgradeCost":2410,"CoolTime":7.5,"DisassemblyTime":5,"Type":3,"id":"HumanTrap","SellPrice":1500},
    {"Level":59,"Attack":0,"Price":3000,"UpgradeCost":2440,"CoolTime":7.5,"DisassemblyTime":5,"Type":3,"id":"HumanTrap","SellPrice":1500},
    {"Level":60,"Attack":0,"Price":3000,"UpgradeCost":2470,"CoolTime":7.5,"DisassemblyTime":5,"Type":3,"id":"HumanTrap","SellPrice":1500},
    {"Level":61,"Attack":0,"Price":3500,"UpgradeCost":2500,"CoolTime":7,"DisassemblyTime":5,"Type":3,"id":"HumanTrap","SellPrice":1750},
    {"Level":62,"Attack":0,"Price":3500,"UpgradeCost":2530,"CoolTime":7,"DisassemblyTime":5,"Type":3,"id":"HumanTrap","SellPrice":1750},
    {"Level":63,"Attack":0,"Price":3500,"UpgradeCost":2560,"CoolTime":7,"DisassemblyTime":5,"Type":3,"id":"HumanTrap","SellPrice":1750},
    {"Level":64,"Attack":0,"Price":3500,"UpgradeCost":2590,"CoolTime":7,"DisassemblyTime":5,"Type":3,"id":"HumanTrap","SellPrice":1750},
    {"Level":65,"Attack":0,"Price":3500,"UpgradeCost":2620,"CoolTime":7,"DisassemblyTime":5,"Type":3,"id":"HumanTrap","SellPrice":1750},
    {"Level":66,"Attack":0,"Price":3500,"UpgradeCost":2650,"CoolTime":7,"DisassemblyTime":5,"Type":3,"id":"HumanTrap","SellPrice":1750},
    {"Level":67,"Attack":0,"Price":3500,"UpgradeCost":2680,"CoolTime":7,"DisassemblyTime":5,"Type":3,"id":"HumanTrap","SellPrice":1750},
    {"Level":68,"Attack":0,"Price":3500,"UpgradeCost":2710,"CoolTime":7,"DisassemblyTime":5,"Type":3,"id":"HumanTrap","SellPrice":1750},
    {"Level":69,"Attack":0,"Price":3500,"UpgradeCost":2740,"CoolTime":7,"DisassemblyTime":5,"Type":3,"id":"HumanTrap","SellPrice":1750},
    {"Level":70,"Attack":0,"Price":3500,"UpgradeCost":2770,"CoolTime":7,"DisassemblyTime":5,"Type":3,"id":"HumanTrap","SellPrice":1750},
    {"Level":71,"Attack":0,"Price":4000,"UpgradeCost":2800,"CoolTime":6.5,"DisassemblyTime":5,"Type":3,"id":"HumanTrap","SellPrice":2000},
    {"Level":72,"Attack":0,"Price":4000,"UpgradeCost":2830,"CoolTime":6.5,"DisassemblyTime":5,"Type":3,"id":"HumanTrap","SellPrice":2000},
    {"Level":73,"Attack":0,"Price":4000,"UpgradeCost":2860,"CoolTime":6.5,"DisassemblyTime":5,"Type":3,"id":"HumanTrap","SellPrice":2000},
    {"Level":74,"Attack":0,"Price":4000,"UpgradeCost":2890,"CoolTime":6.5,"DisassemblyTime":5,"Type":3,"id":"HumanTrap","SellPrice":2000},
    {"Level":75,"Attack":0,"Price":4000,"UpgradeCost":2920,"CoolTime":6.5,"DisassemblyTime":5,"Type":3,"id":"HumanTrap","SellPrice":2000},
    {"Level":76,"Attack":0,"Price":4000,"UpgradeCost":2950,"CoolTime":6.5,"DisassemblyTime":5,"Type":3,"id":"HumanTrap","SellPrice":2000},
    {"Level":77,"Attack":0,"Price":4000,"UpgradeCost":2980,"CoolTime":6.5,"DisassemblyTime":5,"Type":3,"id":"HumanTrap","SellPrice":2000},
    {"Level":78,"Attack":0,"Price":4000,"UpgradeCost":3010,"CoolTime":6.5,"DisassemblyTime":5,"Type":3,"id":"HumanTrap","SellPrice":2000},
    {"Level":79,"Attack":0,"Price":4000,"UpgradeCost":3040,"CoolTime":6.5,"DisassemblyTime":5,"Type":3,"id":"HumanTrap","SellPrice":2000},
    {"Level":80,"Attack":0,"Price":4000,"UpgradeCost":3070,"CoolTime":6.5,"DisassemblyTime":5,"Type":3,"id":"HumanTrap","SellPrice":2000},
    {"Level":81,"Attack":0,"Price":4500,"UpgradeCost":3100,"CoolTime":6,"DisassemblyTime":5,"Type":3,"id":"HumanTrap","SellPrice":2250},
    {"Level":82,"Attack":0,"Price":4500,"UpgradeCost":3130,"CoolTime":6,"DisassemblyTime":5,"Type":3,"id":"HumanTrap","SellPrice":2250},
    {"Level":83,"Attack":0,"Price":4500,"UpgradeCost":3160,"CoolTime":6,"DisassemblyTime":5,"Type":3,"id":"HumanTrap","SellPrice":2250},
    {"Level":84,"Attack":0,"Price":4500,"UpgradeCost":3190,"CoolTime":6,"DisassemblyTime":5,"Type":3,"id":"HumanTrap","SellPrice":2250},
    {"Level":85,"Attack":0,"Price":4500,"UpgradeCost":3220,"CoolTime":6,"DisassemblyTime":5,"Type":3,"id":"HumanTrap","SellPrice":2250},
    {"Level":86,"Attack":0,"Price":4500,"UpgradeCost":3250,"CoolTime":6,"DisassemblyTime":5,"Type":3,"id":"HumanTrap","SellPrice":2250},
    {"Level":87,"Attack":0,"Price":4500,"UpgradeCost":3280,"CoolTime":6,"DisassemblyTime":5,"Type":3,"id":"HumanTrap","SellPrice":2250},
    {"Level":88,"Attack":0,"Price":4500,"UpgradeCost":3310,"CoolTime":6,"DisassemblyTime":5,"Type":3,"id":"HumanTrap","SellPrice":2250},
    {"Level":89,"Attack":0,"Price":4500,"UpgradeCost":3340,"CoolTime":6,"DisassemblyTime":5,"Type":3,"id":"HumanTrap","SellPrice":2250},
    {"Level":90,"Attack":0,"Price":4500,"UpgradeCost":3370,"CoolTime":6,"DisassemblyTime":5,"Type":3,"id":"HumanTrap","SellPrice":2250},
    {"Level":91,"Attack":0,"Price":5000,"UpgradeCost":3400,"CoolTime":5.5,"DisassemblyTime":5,"Type":3,"id":"HumanTrap","SellPrice":2500},
    {"Level":92,"Attack":0,"Price":5000,"UpgradeCost":3430,"CoolTime":5.5,"DisassemblyTime":5,"Type":3,"id":"HumanTrap","SellPrice":2500},
    {"Level":93,"Attack":0,"Price":5000,"UpgradeCost":3460,"CoolTime":5.5,"DisassemblyTime":5,"Type":3,"id":"HumanTrap","SellPrice":2500},
    {"Level":94,"Attack":0,"Price":5000,"UpgradeCost":3490,"CoolTime":5.5,"DisassemblyTime":5,"Type":3,"id":"HumanTrap","SellPrice":2500},
    {"Level":95,"Attack":0,"Price":5000,"UpgradeCost":3520,"CoolTime":5.5,"DisassemblyTime":5,"Type":3,"id":"HumanTrap","SellPrice":2500},
    {"Level":96,"Attack":0,"Price":5000,"UpgradeCost":3550,"CoolTime":5.5,"DisassemblyTime":5,"Type":3,"id":"HumanTrap","SellPrice":2500},
    {"Level":97,"Attack":0,"Price":5000,"UpgradeCost":3580,"CoolTime":5.5,"DisassemblyTime":5,"Type":3,"id":"HumanTrap","SellPrice":2500},
    {"Level":98,"Attack":0,"Price":5000,"UpgradeCost":3610,"CoolTime":5.5,"DisassemblyTime":5,"Type":3,"id":"HumanTrap","SellPrice":2500},
    {"Level":99,"Attack":0,"Price":5000,"UpgradeCost":3640,"CoolTime":5.5,"DisassemblyTime":5,"Type":3,"id":"HumanTrap","SellPrice":2500},
    {"Level":100,"Attack":0,"Price":5000,"UpgradeCost":3670,"CoolTime":5.5,"DisassemblyTime":5,"Type":3,"id":"HumanTrap","SellPrice":2500}]